sectoralarmlib/sector.py
sectoralarmlib-0.9.dist-info/METADATA
sectoralarmlib-0.9.dist-info/WHEEL
sectoralarmlib-0.9.dist-info/top_level.txt
sectoralarmlib-0.9.dist-info/RECORD
